collectionfield/__init__.py
collectionfield/converter.py
collectionfield/forms.py
collectionfield/validators.py
collectionfield/models/__init__.py
collectionfield/models/fields.py
collectionfield/models/lookups.py
collectionfield/tests/__init__.py
collectionfield/tests/forms.py
collectionfield/tests/models.py
collectionfield/tests/tests.py
django_collectionfield-0.0.4.dist-info/DESCRIPTION.rst
django_collectionfield-0.0.4.dist-info/METADATA
django_collectionfield-0.0.4.dist-info/RECORD
django_collectionfield-0.0.4.dist-info/WHEEL
django_collectionfield-0.0.4.dist-info/metadata.json
django_collectionfield-0.0.4.dist-info/top_level.txt
