Metadata-Version: 2.0
Name: django-collectionfield
Version: 0.0.4
Summary: Custom Django model field to store multiple values.
Home-page: https://github.com/escer/django-collectionfield
Author: Pawel Scierski
Author-email: escer@protonmail.com
License: MIT
Keywords: django models fields collections
Platform: UNKNOWN
Classifier: Development Status :: 3 - Alpha
Classifier: Intended Audience :: Developers
Classifier: Environment :: Web Environment
Classifier: License :: OSI Approved :: MIT License
Classifier: Operating System :: OS Independent
Classifier: Programming Language :: Python :: 2
Classifier: Programming Language :: Python :: 2.7
Classifier: Programming Language :: Python :: 3
Classifier: Programming Language :: Python :: 3.4
Classifier: Programming Language :: Python :: 3.5
Classifier: Framework :: Django :: 1.8
Classifier: Framework :: Django :: 1.9
Classifier: Framework :: Django :: 1.10
Classifier: Topic :: Internet :: WWW/HTTP
